refinem
