Metadata-Version: 1.0
Name: refinem
Version: 0.0.23
Summary: A toolbox for improving population genomes.
Home-page: http://pypi.python.org/pypi/refinem/
Author: Donovan Parks
Author-email: donovan.parks@gmail.com
License: GPL3
Platform: UNKNOWN
